monsterui/__init__.py
monsterui/_modidx.py
monsterui/all.py
monsterui/core.py
monsterui/daisy.py
monsterui/foundations.py
monsterui/franken.py
monsterui-1.0.42.dist-info/licenses/LICENSE
monsterui-1.0.42.dist-info/METADATA
monsterui-1.0.42.dist-info/WHEEL
monsterui-1.0.42.dist-info/entry_points.txt
monsterui-1.0.42.dist-info/top_level.txt
monsterui-1.0.42.dist-info/RECORD
