Metadata-Version: 2.4
Name: monsterui
Version: 1.0.42
Summary: The simplicity of FastHTML with the power of Tailwind
Home-page: https://github.com/AnswerDotAI/MonsterUI
Author: isaac flath
Author-email: isaac.flath@gmail.com
License: Apache Software License 2.0
Keywords: nbdev jupyter notebook python
Classifier: Development Status :: 4 - Beta
Classifier: Intended Audience :: Developers
Classifier: Natural Language :: English
Classifier: Programming Language :: Python :: 3.10
Classifier: License :: OSI Approved :: Apache Software License
Requires-Python: >=3.10
License-File: LICENSE
Requires-Dist: python-fasthtml
Requires-Dist: fastcore
Requires-Dist: lxml
Requires-Dist: mistletoe
Requires-Dist: mistlefoot>=0.0.2
Requires-Dist: beautifulsoup4
Provides-Extra: dev
Requires-Dist: pandas; extra == "dev"
Requires-Dist: jinja2; extra == "dev"
Requires-Dist: llms-txt; extra == "dev"
Requires-Dist: pysymbol_llm; extra == "dev"
Dynamic: author
Dynamic: author-email
Dynamic: classifier
Dynamic: description
Dynamic: description-content-type
Dynamic: home-page
Dynamic: keywords
Dynamic: license
Dynamic: license-file
Dynamic: provides-extra
Dynamic: requires-dist
Dynamic: requires-python
Dynamic: summary
